sanic_httpauth.py
sanic_httpauth_compat.py
Sanic_HTTPAuth-0.2.0.dist-info/AUTHORS
Sanic_HTTPAuth-0.2.0.dist-info/LICENSE
Sanic_HTTPAuth-0.2.0.dist-info/METADATA
Sanic_HTTPAuth-0.2.0.dist-info/WHEEL
Sanic_HTTPAuth-0.2.0.dist-info/top_level.txt
Sanic_HTTPAuth-0.2.0.dist-info/RECORD
